echo_tester/__init__.py
echo_tester/apps.py
echo_tester/middleware.py
echo_tester/settings.py
echo_tester/utils.py
echo_tester/logs/__init__.py
echo_tester/management/__init__.py
echo_tester/management/commands/__init__.py
echo_tester/management/commands/runecho.py
echo_tester/parsers/__init__.py
echo_tester/parsers/request.py
echo_tester/parsers/response.py
echo_tester/store/__init__.py
echo_tester/store/store.py
django_echo_tester-0.0.5.dist-info/LICENSE
django_echo_tester-0.0.5.dist-info/METADATA
django_echo_tester-0.0.5.dist-info/WHEEL
django_echo_tester-0.0.5.dist-info/top_level.txt
django_echo_tester-0.0.5.dist-info/RECORD
