Metadata-Version: 2.1
Name: django-echo-tester
Version: 0.0.5
Summary: UNKNOWN
Home-page: https://github.com/mohamed17717/EchoTester
Author: Mhmd
Author-email: d3v.mhmd@gmail.com
License: MIT
Keywords: django tect echo automate
Platform: UNKNOWN
Classifier: Environment :: Web Environment
Classifier: Framework :: Django
Classifier: Intended Audience :: Developers
Classifier: Operating System :: OS Independent
Classifier: Programming Language :: Python :: 3
Classifier: Programming Language :: Python :: 3 :: Only
Classifier: Programming Language :: Python :: 3.5
Classifier: Programming Language :: Python :: 3.6
Classifier: Programming Language :: Python :: 3.7
Classifier: Programming Language :: Python :: 3.8
Classifier: Programming Language :: Python :: 3.9
Classifier: Programming Language :: Python :: 3.10
Classifier: Topic :: Software Development :: Libraries :: Python Modules
Classifier: License :: OSI Approved :: MIT License
License-File: LICENSE
Requires-Dist: Django (>=3.2)
Requires-Dist: requests (>=2.28)
